fluxo_core/__init__.py
fluxo_core/fluxo.py
fluxo_core/init.py
fluxo_core/scheduler.py
fluxo_core/settings.py
fluxo_core/task.py
fluxo_core/utils.py
fluxo_core/database/db.py
fluxo_core/database/fluxo.py
fluxo_core/database/task.py
fluxo_core-0.5.0.dist-info/LICENSE
fluxo_core-0.5.0.dist-info/METADATA
fluxo_core-0.5.0.dist-info/WHEEL
fluxo_core-0.5.0.dist-info/top_level.txt
fluxo_core-0.5.0.dist-info/RECORD
