Metadata-Version: 2.1
Name: fluxo-core
Version: 0.5.0
Summary: Simple data flow with execution in separate threads and easy scheduling configuration.
Author-email: Mailson Náscin <mailson.nascin@gmail.com>
License: MIT
Project-URL: Homepage, https://github.com/nascin/fluxo-core
Project-URL: Source Code, https://github.com/nascin/fluxo-core
Project-URL: Bug Tracker, https://github.com/nascin/fluxo-core/issues
Keywords: fluxo,fluxo-core,data,scheduler
Classifier: Programming Language :: Python :: 3
Classifier: Intended Audience :: Developers
Classifier: License :: OSI Approved :: MIT License
Classifier: Operating System :: OS Independent
Classifier: Topic :: Software Development :: Internationalization
Requires-Python: >=3.11
License-File: LICENSE
Requires-Dist: schedule ==1.2.1
